{
  "version": "7",
  "dialect": "mysql",
  "entries": [
    {
      "idx": 0,
      "version": "5",
      "when": 1770570442748,
      "tag": "0000_heavy_silver_surfer",
      "breakpoints": true
    },
    {
      "idx": 1,
      "version": "5",
      "when": 1770572098076,
      "tag": "0001_brave_ender_wiggin",
      "breakpoints": true
    },
    {
      "idx": 2,
      "version": "5",
      "when": 1770786844786,
      "tag": "0002_mature_gambit",
      "breakpoints": true
    },
    {
      "idx": 3,
      "version": "5",
      "when": 1770802858585,
      "tag": "0003_cloudy_masque",
      "breakpoints": true
    }
  ]
}